mysingle/__init__.py
mysingle/constants.py
mysingle/audit/__init__.py
mysingle/audit/middleware.py
mysingle/audit/models.py
mysingle/auth/README.md
mysingle/auth/__init__.py
mysingle/auth/authenticate.py
mysingle/auth/cache.py
mysingle/auth/exception_handlers.py
mysingle/auth/exceptions.py
mysingle/auth/init_data.py
mysingle/auth/middleware.py
mysingle/auth/models.py
mysingle/auth/oauth_manager.py
mysingle/auth/types.py
mysingle/auth/user_manager.py
mysingle/auth/deps/__init__.py
mysingle/auth/deps/core.py
mysingle/auth/deps/decorators.py
mysingle/auth/deps/kong.py
mysingle/auth/deps/permissions.py
mysingle/auth/oauth2/clients.py
mysingle/auth/router/__init__.py
mysingle/auth/router/auth.py
mysingle/auth/router/common.py
mysingle/auth/router/oauth2.py
mysingle/auth/router/oauth_management.py
mysingle/auth/router/register.py
mysingle/auth/router/reset.py
mysingle/auth/router/users.py
mysingle/auth/router/verify.py
mysingle/auth/schemas/__init__.py
mysingle/auth/schemas/auth.py
mysingle/auth/schemas/oauth2.py
mysingle/auth/schemas/user.py
mysingle/auth/security/cookie.py
mysingle/auth/security/jwt.py
mysingle/auth/security/password.py
mysingle/base/__init__.py
mysingle/base/enums.py
mysingle/base/models.py
mysingle/base/schemas.py
mysingle/clients/__init__.py
mysingle/clients/base_client.py
mysingle/clients/base_grpc_client.py
mysingle/core/__init__.py
mysingle/core/app_factory.py
mysingle/core/config.py
mysingle/core/db.py
mysingle/core/http_client.py
mysingle/core/middleware.py
mysingle/core/service_types.py
mysingle/database/__init__.py
mysingle/database/duckdb_manager.py
mysingle/dsl/README.md
mysingle/dsl/__init__.py
mysingle/dsl/errors.py
mysingle/dsl/executor.py
mysingle/dsl/limits.py
mysingle/dsl/parser.py
mysingle/dsl/stdlib.py
mysingle/dsl/validator.py
mysingle/email/__init__.py
mysingle/email/email_gen.py
mysingle/email/email_sending.py
mysingle/email/email_token.py
mysingle/email/email-templates/logo.png
mysingle/examples/__init__.py
mysingle-1.4.8.dist-info/METADATA
mysingle-1.4.8.dist-info/WHEEL
mysingle-1.4.8.dist-info/RECORD
