Metadata-Version: 2.4
Name: mysingle
Version: 1.4.8
Summary: Common utilities and configurations for MySingle Platform microservices
Requires-Python: >=3.12
Requires-Dist: aiohttp>=3.9.4
Requires-Dist: beanie>=1.23.6
Requires-Dist: colorlog>=6.9.0
Requires-Dist: duckdb>=1.1.0
Requires-Dist: email-validator>=2.2.0
Requires-Dist: emails>=0.6
Requires-Dist: fastapi>=0.104.1
Requires-Dist: grpcio>=1.60.0
Requires-Dist: httpx-oauth>=0.16.1
Requires-Dist: httpx>=0.25.2
Requires-Dist: jinja2>=3.1.6
Requires-Dist: makefun>=1.16.0
Requires-Dist: motor>=3.3.2
Requires-Dist: numpy>=1.26.0
Requires-Dist: pandas>=2.2.0
Requires-Dist: prometheus-client>=0.19.0
Requires-Dist: pwdlib[argon2,bcrypt]>=0.2.1
Requires-Dist: pydantic-settings>=2.1.0
Requires-Dist: pydantic>=2.5.0
Requires-Dist: pyjwt>=2.10.1
Requires-Dist: python-multipart>=0.0.6
Requires-Dist: redis>=6.4.0
Requires-Dist: restrictedpython>=7.0
Requires-Dist: structlog>=23.2.0
Requires-Dist: uvicorn[standard]>=0.24.0
Provides-Extra: dev
Requires-Dist: httpx>=0.26.0; extra == 'dev'
Requires-Dist: mypy>=1.8.0; extra == 'dev'
Requires-Dist: pytest-asyncio>=0.21.1; extra == 'dev'
Requires-Dist: pytest>=7.4.3; extra == 'dev'
Requires-Dist: ruff>=0.1.9; extra == 'dev'
